patch_target/__init__.py
patch_target/py.typed
patch_target-0.1.10.dist-info/METADATA
patch_target-0.1.10.dist-info/WHEEL
patch_target-0.1.10.dist-info/RECORD
