Metadata-Version: 2.1
Name: patch-target
Version: 0.1.10
Summary: Create unittest.mock.patch target values from python modules instead of string wrangling
Home-page: https://github.com/bboggs-streambit/patch-target
License: MIT
Author: brad.boggs
Author-email: bradleywboggs@protonmail.com
Requires-Python: >=3.10,<4.0
Classifier: License :: OSI Approved :: MIT License
Classifier: Programming Language :: Python :: 3
Classifier: Programming Language :: Python :: 3.10
Classifier: Programming Language :: Python :: 3.11
Project-URL: Repository, https://github.com/bboggs-streambit/patch-target
